sfpy/float.so
sfpy/__init__.py
sfpy/posit.so
sfpy/lib/softfloat.a
sfpy/lib/softposit.a
sfpy/include/softfloat_types.h
sfpy/include/softposit_types.h
sfpy/include/softfloat.h
sfpy/include/softposit.h
sfpy-0.6.0.dist-info/top_level.txt
sfpy-0.6.0.dist-info/RECORD
sfpy-0.6.0.dist-info/WHEEL
sfpy-0.6.0.dist-info/METADATA
