Metadata-Version: 2.1
Name: sfpy
Version: 0.6.0
Summary: softfloat and softposit in python
Home-page: https://github.com/billzorn/sfpy
Author: Bill Zorn
Author-email: bill.zorn@gmail.com
License: UNKNOWN
Platform: UNKNOWN
Classifier: Development Status :: 4 - Beta
Classifier: Operating System :: POSIX :: Linux
Classifier: Programming Language :: Python :: 2.7
Classifier: Programming Language :: Python :: 3.5
Classifier: Programming Language :: Python :: 3.6
Classifier: Programming Language :: Python :: 3.7
Classifier: License :: OSI Approved :: MIT License
